ligrad/__init__.py
ligrad/main.py
ligrad-1.0.0.dist-info/licenses/LICENSE.txt
ligrad-1.0.0.dist-info/METADATA
ligrad-1.0.0.dist-info/WHEEL
ligrad-1.0.0.dist-info/top_level.txt
ligrad-1.0.0.dist-info/RECORD
