Metadata-Version: 2.4
Name: ligrad
Version: 1.0.0
License-File: LICENSE.txt
Requires-Dist: numpy>=1.17
Requires-Dist: scipy>=1.5
Requires-Dist: astropy>=4.0
Requires-Dist: pylightcurve>=2.0
Dynamic: description
Dynamic: description-content-type
Dynamic: license-file
Dynamic: requires-dist
